odoo/addons/pos_customer_required/README.rst
odoo/addons/pos_customer_required/__init__.py
odoo/addons/pos_customer_required/__manifest__.py
odoo/addons/pos_customer_required/i18n/ca.po
odoo/addons/pos_customer_required/i18n/es.po
odoo/addons/pos_customer_required/i18n/fr.po
odoo/addons/pos_customer_required/i18n/it.po
odoo/addons/pos_customer_required/i18n/nl_NL.po
odoo/addons/pos_customer_required/i18n/pos_customer_required.pot
odoo/addons/pos_customer_required/models/__init__.py
odoo/addons/pos_customer_required/models/pos_config.py
odoo/addons/pos_customer_required/models/pos_make_payment.py
odoo/addons/pos_customer_required/models/pos_order.py
odoo/addons/pos_customer_required/readme/CONFIGURE.rst
odoo/addons/pos_customer_required/readme/CONTRIBUTORS.rst
odoo/addons/pos_customer_required/readme/DESCRIPTION.rst
odoo/addons/pos_customer_required/readme/USAGE.rst
odoo/addons/pos_customer_required/static/description/frontend_pos_error_message.png
odoo/addons/pos_customer_required/static/description/icon.png
odoo/addons/pos_customer_required/static/description/index.html
odoo/addons/pos_customer_required/static/src/js/gui.js
odoo/addons/pos_customer_required/static/src/js/screens.js
odoo/addons/pos_customer_required/tests/__init__.py
odoo/addons/pos_customer_required/tests/test_pos.py
odoo/addons/pos_customer_required/views/assets.xml
odoo/addons/pos_customer_required/views/pos_config_view.xml
odoo/addons/pos_customer_required/views/pos_order_view.xml
odoo13_addon_pos_customer_required-13.0.1.0.1.dev7.dist-info/METADATA
odoo13_addon_pos_customer_required-13.0.1.0.1.dev7.dist-info/WHEEL
odoo13_addon_pos_customer_required-13.0.1.0.1.dev7.dist-info/top_level.txt
odoo13_addon_pos_customer_required-13.0.1.0.1.dev7.dist-info/RECORD
